adrf/__init__.py
adrf/decorators.py
adrf/fields.py
adrf/generics.py
adrf/mixins.py
adrf/requests.py
adrf/routers.py
adrf/serializers.py
adrf/shortcuts.py
adrf/test.py
adrf/utils.py
adrf/views.py
adrf/viewsets.py
adrf-0.1.11.dist-info/METADATA
adrf-0.1.11.dist-info/WHEEL
adrf-0.1.11.dist-info/licenses/LICENSE
adrf-0.1.11.dist-info/RECORD
