Metadata-Version: 2.4
Name: adrf
Version: 0.1.11
Summary: Async support for Django REST framework
License: MIT
License-File: LICENSE
Keywords: async,django,rest,framework,drf
Author: Enrico Massa
Author-email: enrico.massa@gmail.com
Requires-Python: >=3.8
Classifier: License :: OSI Approved :: MIT License
Classifier: Programming Language :: Python :: 3
Classifier: Programming Language :: Python :: 3.8
Classifier: Programming Language :: Python :: 3.9
Classifier: Programming Language :: Python :: 3.10
Classifier: Programming Language :: Python :: 3.11
Classifier: Programming Language :: Python :: 3.12
Classifier: Programming Language :: Python :: 3.13
Classifier: Programming Language :: Python :: 3.14
Requires-Dist: async-property (>=0.2.2)
Requires-Dist: django (>=4.1)
Requires-Dist: djangorestframework (>=3.14.0)
Project-URL: Homepage, https://github.com/em1208/adrf
Project-URL: Repository, https://github.com/em1208/adrf
